odoo9_addon_subcontracted_service-9.0.1.0.0.99.dev12-py2.7-nspkg.pth
odoo9_addon_subcontracted_service-9.0.1.0.0.99.dev12.dist-info/DESCRIPTION.rst
odoo9_addon_subcontracted_service-9.0.1.0.0.99.dev12.dist-info/METADATA
odoo9_addon_subcontracted_service-9.0.1.0.0.99.dev12.dist-info/RECORD
odoo9_addon_subcontracted_service-9.0.1.0.0.99.dev12.dist-info/WHEEL
odoo9_addon_subcontracted_service-9.0.1.0.0.99.dev12.dist-info/metadata.json
odoo9_addon_subcontracted_service-9.0.1.0.0.99.dev12.dist-info/namespace_packages.txt
odoo9_addon_subcontracted_service-9.0.1.0.0.99.dev12.dist-info/top_level.txt
odoo_addons/subcontracted_service/README.rst
odoo_addons/subcontracted_service/__init__.py
odoo_addons/subcontracted_service/__openerp__.py
odoo_addons/subcontracted_service/init_hook.py
odoo_addons/subcontracted_service/i18n/ca.po
odoo_addons/subcontracted_service/i18n/de.po
odoo_addons/subcontracted_service/i18n/el_GR.po
odoo_addons/subcontracted_service/i18n/es.po
odoo_addons/subcontracted_service/i18n/es_ES.po
odoo_addons/subcontracted_service/i18n/es_MX.po
odoo_addons/subcontracted_service/i18n/eu.po
odoo_addons/subcontracted_service/i18n/fi.po
odoo_addons/subcontracted_service/i18n/fr.po
odoo_addons/subcontracted_service/i18n/fr_CH.po
odoo_addons/subcontracted_service/i18n/fr_FR.po
odoo_addons/subcontracted_service/i18n/gl.po
odoo_addons/subcontracted_service/i18n/hr.po
odoo_addons/subcontracted_service/i18n/hr_HR.po
odoo_addons/subcontracted_service/i18n/it.po
odoo_addons/subcontracted_service/i18n/nl.po
odoo_addons/subcontracted_service/i18n/nl_NL.po
odoo_addons/subcontracted_service/i18n/pt.po
odoo_addons/subcontracted_service/i18n/pt_BR.po
odoo_addons/subcontracted_service/i18n/pt_PT.po
odoo_addons/subcontracted_service/i18n/ro.po
odoo_addons/subcontracted_service/i18n/ru.po
odoo_addons/subcontracted_service/i18n/sk.po
odoo_addons/subcontracted_service/i18n/sl.po
odoo_addons/subcontracted_service/i18n/tr.po
odoo_addons/subcontracted_service/i18n/tr_TR.po
odoo_addons/subcontracted_service/i18n/vi_VN.po
odoo_addons/subcontracted_service/i18n/zh_CN.po
odoo_addons/subcontracted_service/models/__init__.py
odoo_addons/subcontracted_service/models/procurement.py
odoo_addons/subcontracted_service/models/product.py
odoo_addons/subcontracted_service/models/warehouse.py
odoo_addons/subcontracted_service/static/description/icon.png
odoo_addons/subcontracted_service/tests/__init__.py
odoo_addons/subcontracted_service/tests/test_subcontracted_service.py
